evntaly_python/__init__.py
evntaly_python/_version.py
evntaly_python/sdk.py
evntaly_python-1.0.20.dist-info/LICENSE
evntaly_python-1.0.20.dist-info/METADATA
evntaly_python-1.0.20.dist-info/WHEEL
evntaly_python-1.0.20.dist-info/top_level.txt
evntaly_python-1.0.20.dist-info/RECORD
