Metadata-Version: 2.2
Name: evntaly_python
Version: 1.0.20
Summary: A Python SDK for Evntaly event tracking platform
Home-page: https://github.com/Evntaly/evntaly-python
Author: Alameer Ashraf
Author-email: alameer@evntaly.com
Classifier: Programming Language :: Python :: 3
Classifier: License :: OSI Approved :: MIT License
Classifier: Operating System :: OS Independent
Requires-Python: >=3.7
License-File: LICENSE
Requires-Dist: requests
Dynamic: author
Dynamic: author-email
Dynamic: classifier
Dynamic: description
Dynamic: description-content-type
Dynamic: home-page
Dynamic: requires-dist
Dynamic: requires-python
Dynamic: summary
